oganesson_py/__init__.py
oganesson_py/analyser/__init__.py
oganesson_py/analyser/analyser.py
oganesson_py/analyser/builder.py
oganesson_py/analyser/cyclomatic_complexity.py
oganesson_py/analyser/maintainability_index.py
oganesson_py/analysis.py
oganesson_py/exceptions.py
oganesson_py/filetree.py
oganesson_py/main.py
oganesson_py/reporter.py
oganesson_py/validators.py
oganesson_py-0.1.1.dist-info/LICENSE
oganesson_py-0.1.1.dist-info/METADATA
oganesson_py-0.1.1.dist-info/WHEEL
oganesson_py-0.1.1.dist-info/entry_points.txt
oganesson_py-0.1.1.dist-info/RECORD
